Workbook

Sheet Simulador
A1: FULANO INVEST | SIMULADOR DE FIIS
A5: CONFIGURAÇÕES
A6: Salário | B6: 2000
A7: Rendimento Carteira | B7: 0.006
A8: Sugestão de Investimento (30%) | B8: =B6*0.3
A10: INVESTIMENTO MENSAL
A11: Quanto investir por mês ? | B11: 200
A12: Por Quantos Anos ? | B12: 5
A13: Taxa de Rendimento mensal ? | B13: 0.01079
A14: Patrimônio acumulado ? | B14: =VF(B13; B12*12; -B11; 0)
A15: Dividendos Mensais ? | B15: =B14*B7
A17: Cenários (Anos) | B17: Patrimônio | C17: Dividendo
A18: 2 | B18: =VF($B$13; A18*12; -$B$11; 0) | C18: =B18*$B$7
A19: 5 | B19: =VF($B$13; A19*12; -$B$11; 0) | C19: =B19*$B$7
A20: 10 | B20: =VF($B$13; A20*12; -$B$11; 0) | C20: =B20*$B$7
A21: 20 | B21: =VF($B$13; A21*12; -$B$11; 0) | C21: =B21*$B$7
A22: 30 | B22: =VF($B$13; A22*12; -$B$11; 0) | C22: =B22*$B$7
A24: PERFIL SELECIONADO: | B24: Moderado
A26: TIPO DE FII | B26: Percentual Sugerido | C26: Valores
A27: PAPEL | B27: =PROCV($B$24&"-"&A27; Apoio_Dados!A:D; 4; FALSO) | C27: =$B$11*B27
A28: TIJOLO | B28: =PROCV($B$24&"-"&A28; Apoio_Dados!A:D; 4; FALSO) | C28: =$B$11*B28
A29: HÍBRIDOS | B29: =PROCV($B$24&"-"&A29; Apoio_Dados!A:D; 4; FALSO) | C29: =$B$11*B29
A30: FOFs | B30: =PROCV($B$24&"-"&A30; Apoio_Dados!A:D; 4; FALSO) | C30: =$B$11*B30
A31: DESENVOLVIMENTO | B31: =PROCV($B$24&"-"&A31; Apoio_Dados!A:D; 4; FALSO) | C31: =$B$11*B31
A32: HOTELARIAS | B32: =PROCV($B$24&"-"&A32; Apoio_Dados!A:D; 4; FALSO) | C32: =$B$11*B32
A33: Total | B33: =SUM(B27:B32) | C33: =SUM(C27:C32)

Sheet Apoio_Dados
A1: CHAVE | B1: PERFIL | C1: TIPO DE FII | D1: %
A2: Conservador-PAPEL | B2: Conservador | C2: PAPEL | D2: 0.3
A3: Conservador-TIJOLO | B3: Conservador | C3: TIJOLO | D3: 0.5
A4: Conservador-HÍBRIDOS | B4: Conservador | C4: HÍBRIDOS | D4: 0.1
A5: Conservador-FOFs | B5: Conservador | C5: FOFs | D5: 0.1
A6: Conservador-DESENVOLVIMENTO | B6: Conservador | C6: DESENVOLVIMENTO | D6: 0
A7: Conservador-HOTELARIAS | B7: Conservador | C7: HOTELARIAS | D7: 0
A8: Moderado-PAPEL | B8: Moderado | C8: PAPEL | D8: 0.32
A9: Moderado-TIJOLO | B9: Moderado | C9: TIJOLO | D9: 0.35
A10: Moderado-HÍBRIDOS | B10: Moderado | C10: HÍBRIDOS | D10: 0.08
A11: Moderado-FOFs | B11: Moderado | C11: FOFs | D11: 0.05
A12: Moderado-DESENVOLVIMENTO | B12: Moderado | C12: DESENVOLVIMENTO | D12: 0.1
A13: Moderado-HOTELARIAS | B13: Moderado | C13: HOTELARIAS | D13: 0.1
... A19: Agressivo-HOTELARIAS | B19: Agressivo | C19: HOTELARIAS | D19: 0.1
